{
    "nodes": [
        {"id": "A", "x": 100, "y": 150},
        {"id": "B", "x": 200, "y": 200},
        {"id": "C", "x": 300, "y": 400},
        {"id": "D", "x": 400, "y": 400},
        {"id": "E", "x": 400, "y": 450}
    ],
    "edges": [
        {"start": "A", "end": "B", "weight": 5},
        {"start": "B", "end": "C", "weight": 3},
        {"start": "C", "end": "A", "weight": 1},
        {"start": "D", "end": "E", "weight": 2},
        {"start": "E", "end": "D", "weight": 4},
        {"start": "A", "end": "D", "weight": 2},
        {"start": "B", "end": "E", "weight": 1},
        {"start": "C", "end": "D", "weight": 2},
        {"start": "D", "end": "B", "weight": 1},
        {"start": "E", "end": "C", "weight": 3}
    ]
    
}